paramsparser/__init__.py
paramsparser/config2params.py
paramsparser/dict2params.py
paramsparser/json2params.py
paramsparser/paramsbase.py
paramsparser/yaml2params.py
paramsparser-2.1.0.dist-info/METADATA
paramsparser-2.1.0.dist-info/WHEEL
paramsparser-2.1.0.dist-info/top_level.txt
paramsparser-2.1.0.dist-info/RECORD
