Metadata-Version: 2.1
Name: paramsparser
Version: 2.1.0
Summary: Parse parameters written in files.
Home-page: https://github.com/pysan3/paramsparser.git
Author: pysan3
Author-email: pysan3@gmail.com
License: MIT
Keywords: paramsparser yaml PyYAML ConfigParser json
Platform: UNKNOWN
Classifier: License :: OSI Approved :: MIT License
Classifier: Programming Language :: Python :: 3.8
Requires-Dist: PyYAML
Requires-Dist: ConfigParser
